<?xml version='1.0' encoding='UTF-8'?>
<webservice-policy-ref xmlns="http://www.bea.com/ns/weblogic/90" xmlns:xsi="http://www.w3.org/2001/XMLSchema-instance">
    <port-policy>
        <port-name>ApplicationsSecure</port-name>
        <ws-policy>
            <uri>policy:SVAP_policy.xml</uri>
            <direction>both</direction>
        </ws-policy>
    </port-policy>

    <port-policy>
        <port-name>CardbatchSOAP</port-name>
        <ws-policy>
            <uri>policy:Cardbatch_policy.xml</uri>
            <direction>both</direction>
        </ws-policy>
    </port-policy>

    <port-policy>
        <port-name>InstantIssueSOAP</port-name>
        <ws-policy>
            <uri>policy:InstantIssue_policy.xml</uri>
            <direction>both</direction>
        </ws-policy>
    </port-policy>
</webservice-policy-ref>